{
  "productName": "sv-playbook",
  "chatLanguage": "en",
  "tier": "TIER-2",
  "verifyCommand": "npm run verify",
  "reviewCandidateMaxBytes": 16777216,
  "autonomy": "strict",
  "backup": {
    "enabled": true,
    "retention": 3,
    "maxAgeHours": 24,
    "onEvents": ["done"]
  },
  "modelEvaluation": {
    "evidenceValidityDays": 30
  },
  "gates": {
    "maxLines": 350,
    "maxLinesPerFunction": 60,
    "complexity": 10,
    "cognitiveComplexity": 10,
    "layout": true
  },
  "baseline": {
    "ormApplicationSql": {
      "count": 282,
      "digest": "a136a6c52767eb88c0ab7152aaa9a4f316e3dfa970d286a9be1c4a30ad5f3597"
    },
    "literalComparisons": {
      "count": 278,
      "digest": "13f1a30efdac3f9fa079f884404100664e5bb2aed0956db209e16b05a80b62cf"
    },
    "duplicateStrings": {
      "count": 1401,
      "digest": "684a4e5fd76b6013919b07d2b422065e4b59d5b7ef45b0313ea40ab23028e298"
    },
    "fingerprints": [
      "docs/packets/ADOPT-AURORA-001.md",
      "docs/packets/CLI-QUIET-001.md",
      "docs/packets/CONSTITUTION-CLEANUP-001.md",
      "docs/packets/DOCS-CLI-STORE-001.md",
      "docs/packets/DOGFOOD-CONSTITUTION-001.md",
      "docs/packets/DROP-ROTATE-001.md",
      "docs/packets/FLOW-WORKTREE-001.md",
      "docs/packets/OPINION-FREE-CORE-001.md",
      "docs/packets/PROCESS-GATE-001.md",
      "docs/packets/ROLE-ORCHESTRATOR-001.md",
      "docs/packets/ROLE-ORCHESTRATOR-HARDEN-001.md",
      "docs/packets/SERVE-DETAIL-001.md",
      "docs/packets/SKILL-REPO-STATE-001.md",
      "docs/packets/TASTE-LEDGER-001.md",
      "docs/packets/TEST-QUIET-001.md"
    ]
  }
}
